infvariation/__init__.py
infvariation/variations.py
infvariation-0.1.2.dist-info/METADATA
infvariation-0.1.2.dist-info/WHEEL
infvariation-0.1.2.dist-info/top_level.txt
infvariation-0.1.2.dist-info/RECORD
