Metadata-Version: 2.1
Name: infvariation
Version: 0.1.2
Summary: A Python library for generating information variations, such as typo-squatting domains, leet transformations, and custom text variations.
Home-page: https://github.com/gomesrocha/infvariation
Author: Fabio Gomes Rocha
Author-email: gomesrocha@gmail.com
Classifier: Programming Language :: Python :: 3
Classifier: License :: OSI Approved :: Apache Software License
Classifier: Operating System :: OS Independent
Requires-Python: >=3.8
Requires-Dist: ail-typo-squatting
Requires-Dist: leet
